README.rst
appflow
appflow.py
setup.cfg
setup.py
appflow.egg-info/PKG-INFO
appflow.egg-info/SOURCES.txt
appflow.egg-info/dependency_links.txt
appflow.egg-info/requires.txt
appflow.egg-info/top_level.txt
lib/__init__.py
lib/appflow_ansible.py
lib/appflow_tools.py
lib/appflow_utils.py
lib/appflow_yaml.py