Metadata-Version: 1.1
Name: appflow
Version: 1.0.1.5
Summary: AppFlow is a multitenant environment automation tool based on Ansible.
Home-page: https://github.com/ttssdev/appflow
Author: TTSS
Author-email: dev@appflow.com
License: AGPLv3
Keywords: ansible tenant provision deploy setuptools development
Platform: UNKNOWN
Classifier: Development Status :: 3 - Alpha
Classifier: Intended Audience :: Developers
Classifier: Topic :: Software Development :: Build Tools
Classifier: License :: OSI Approved :: GNU Affero General Public License v3
Classifier: Programming Language :: Python :: 3
Classifier: Programming Language :: Python :: 3.4
Classifier: Programming Language :: Python :: 3.5
Classifier: Programming Language :: Python :: 3.6
